md_resume/__init__.py
md_resume-0.2.7.dist-info/LICENSE
md_resume-0.2.7.dist-info/METADATA
md_resume-0.2.7.dist-info/WHEEL
md_resume-0.2.7.dist-info/entry_points.txt
md_resume-0.2.7.dist-info/top_level.txt
md_resume-0.2.7.dist-info/RECORD
