Metadata-Version: 2.1
Name: md-resume
Version: 0.2.7
Summary: markdown resume prettifier
Home-page: https://github.com/yiwensong/resume
Author: yiwen song
Author-email: songzgy@gmail.com
License: MIT
Keywords: resume,markdown,pretty,yiwen
Classifier: Natural Language :: English
Classifier: Programming Language :: Python :: 3.7
License-File: LICENSE
Requires-Dist: Markdown
